core/__init__.py
core/server.py
core/database/__init__.py
core/database/influx.py
core/email/__init__.py
core/email/mail_handler.py
core/email/site_list.py
core/log/__init__.py
core/log/seq.py
core/settings/__init__.py
core/settings/settings.py
tif_monitor_core-3.0.12.dist-info/LICENSE
tif_monitor_core-3.0.12.dist-info/METADATA
tif_monitor_core-3.0.12.dist-info/WHEEL
tif_monitor_core-3.0.12.dist-info/top_level.txt
tif_monitor_core-3.0.12.dist-info/RECORD
