Metadata-Version: 2.1
Name: tif-monitor-core
Version: 3.0.12
Summary: A basic task scheduler
Home-page: UNKNOWN
Author: Sam Hampton
License: UNKNOWN
Platform: UNKNOWN
Classifier: Programming Language :: Python :: 3
Classifier: License :: OSI Approved :: MIT License
Classifier: Operating System :: OS Independent
